{
    "TUBITV2_OLED_CATEGORY": "OLED",
    "TUBITV2_OLED_START": "oled start",
    "TUBITV2_OLED_UPDATE": "update display",
    "TUBITV2_OLED_CLEAR": "clear display",
    "TUBITV2_OLED_DRAWRLINE":"draw line x: %1 y: %2 x1: %3 y1: %4",
    "TUBITV2_OLED_DRAWAXISALIGNEDLINE": "draw axis-aligned line x: %1 y: %2 length %3 , %4",
    "TUBITV2_OLED_DRAWRECTANGLE":"draw rectangle x: %1 y: %2 width %3 height %4 rounded corners %5 , %6",
    "TUBITV2_OLED_DRAWRCIRCLE":"draw circle x: %1 y: %2 radius %3 , %4",
    "TUBITV2_OLED_DRAWRTRIANGLE":"draw triangle x: %1 y: %2 x1: %3 y1: %4 x2: %5 y2: %6 , %7",
    "TUBITV2_OLED_DRAWSTRING":"draw string x: %1 y: %2 %3",
    "TUBITV2_OLED_FILLED":"Filled",
    "TUBITV2_OLED_HOLLOW":"Hollow",
    "TUBITV2_OLED_VERTICAL":"Vertical",
    "TUBITV2_OLED_HORIZONTAL":"Horizontal",
    "TUBITV2_OLED_LABEL_ADVANCE_A": "OLED: Draw Shapes",
    "TUBITV2_OLED_LABEL_ADVANCE_B": "OLED: Draw String",
    "TUBITV2_OLED_LABEL_ADVANCE_C": "OLED: Draw Chart",
    "TUBITV2_OLED_LABEL_ADVANCE_D": "OLED: Animations",
    "TUBITV2_OLED_RIGHT": "Right",
    "TUBITV2_OLED_LEFT": "Left",
    "TUBITV2_OLED_UP": "Up",
    "TUBITV2_OLED_DOWN": "Down",
    "TUBITV2_OLED_ANIMUPDATE": "update display",
    "TUBITV2_OLED_ANIMDONTUPDATE": "don't update display",
    "TUBITV2_OLED_ANIMDRAWEYES": "draw eyes, %1",
    "TUBITV2_OLED_ANIMRESETEYES": "reset eyes, %1",
    "TUBITV2_OLED_ANIMWAKEUP": "wakeup ",
    "TUBITV2_OLED_ANIMBLINK": "blink, speed: %1",
    "TUBITV2_OLED_ANIMHAPPYEYE": "happy eye",
    "TUBITV2_OLED_ANIMANGRYEYE": "angry eye",
    "TUBITV2_OLED_ANIMTIREDEYE": "tired eye",
    "TUBITV2_OLED_ANIMLEFTWINKEYE": "left wink",
    "TUBITV2_OLED_ANIMMOVEBIGEYE": "move big eye, direction: %1",
    "TUBITV2_OLED_ANIMSACCADE": "saccade, direction x: %1 y: %2",
    "TUBITV2_OLED_ANIMLAUNCHANIMATIONWITHINDEX": "play animation id: %1",
    "TUBITV2_OLED_DRAWCHART": "chart data: %1 chart type: %2 start from: %3",
    "TUBITV2_OLED_CHART_BAR": "Bar",
    "TUBITV2_OLED_CHART_LINE": "Line",
    "TUBITV2_OLED_SAVEBITMAP": "add bitmap %1",
    "TUBITV2_OLED_DRAWBITMAP": "draw bitmap x: %1 y: %2 width %3 height %4",
    "TUBITV2_OLED_WAKEUP": "Wake up eyes",
    "TUBITV2_OLED_RESETEYE": "Reset eyes",
    "TUBITV2_OLED_MBE_RIGHT": "Move big eye right",
    "TUBITV2_OLED_MBE_LEFT": "Move big eye left",
    "TUBITV2_OLED_BLINK_WAIT": "Blink (with pause)",
    "TUBITV2_OLED_HAPPY": "Happy eyes",
    "TUBITV2_OLED_BLINK": "Blink",
    "TUBITV2_OLED_LEFTWINK": "Left wink",
    "TUBITV2_OLED_ANGRY": "Angry eyes",
    "TUBITV2_OLED_SACCADE": "Random saccade",
    "TUBITV2_OLED_CREATEIMAGE": "create image %1 , BMP = %2",
    "TUBITV2_OLED_DISPLAYIMAGE": "display image %5 , x: %1 y: %2 width %3 height %4",
    "TUBITV2_OLED_LABEL_ADVANCE_BA": "OLED: Image",
    "TUBITV2_OLED_FONT": "Font %1 , x: %2 y: %3 print: %4",
    "TUBITV2_OLED_EN": "English",
    "TUBITV2_OLED_CHINESE": "Chinese",
    "TUBITV2_OLED_MATRIX": "draw %1"
}
